recoverable_async_task.py
recoverable_async_task-0.2.4.dist-info/METADATA
recoverable_async_task-0.2.4.dist-info/WHEEL
recoverable_async_task-0.2.4.dist-info/RECORD
