Metadata-Version: 2.4
Name: recoverable-async-task
Version: 0.2.4
Summary: `recoverable-async-task` is a Python library that streamlines the handling of asynchronous tasks through its `RecoverableAsyncTask` class, with the added benefit of **supporting task checkpointing and resumption**. This feature ensures that tasks can pick up from where they left off in the event of unexpected failures.
Project-URL: Homepage, https://github.com/Haskely/recoverable-async-task
Project-URL: Bug Reports, https://github.com/Haskely/recoverable-async-task/issues
Project-URL: Source, https://github.com/Haskely/recoverable-async-task
Author-email: Haskely <Haskely@live.com>
Requires-Python: >=3.10
Requires-Dist: loguru>=0.7.2
Requires-Dist: tqdm>=4.66.2
Requires-Dist: typing-extensions>=4.11.0
